example/create_test_plots.py
example/example_images/batch_comparison_example.html
example/example_images/batch_comparison_example.png
example/example_images/batch_comparison_selection_example.png
example/example_images/superlineage_example.png
example/summarized_example.html
example/superlineage_example.html
example/wastewater-freyja-aggregated.tsv
example/wastewater-freyja-compare1.tsv
example/wastewater-freyja-compare2.tsv
freyja_plot/__init__.py
freyja_plot/freyja_plot.py
freyja_plot/main.py
freyja_plot/version.py
freyja_plot-0.8.3.dist-info/LICENSE
freyja_plot-0.8.3.dist-info/METADATA
freyja_plot-0.8.3.dist-info/WHEEL
freyja_plot-0.8.3.dist-info/entry_points.txt
freyja_plot-0.8.3.dist-info/RECORD
