Metadata-Version: 2.1
Name: freyja-plot
Version: 0.8.3
Summary: Plotting lineage abundance for individual samples from aggregated freyja demix results
Home-page: https://github.com/enviro-lab/freyja-plot.git
License: MIT
Keywords: freyja,plot,lineage,abundance,covid
Author: Sam Kunkleman
Author-email: skunklem@uncc.edu
Requires-Python: >=3.8,<4.0
Classifier: License :: OSI Approved :: MIT License
Classifier: Programming Language :: Python :: 3
Classifier: Programming Language :: Python :: 3.8
Classifier: Programming Language :: Python :: 3.9
Classifier: Programming Language :: Python :: 3.10
Classifier: Programming Language :: Python :: 3.11
Requires-Dist: kaleido (==0.1.0)
Requires-Dist: pandas (>=2.0.1,<3.0.0)
Requires-Dist: plotly (>=5.14.1,<6.0.0)
Requires-Dist: pyyaml (>=6.0,<7.0)
Project-URL: Repository, https://github.com/enviro-lab/freyja-plot.git
